ShellPride/__init__.py
ShellPride/colors/__init__.py
ShellPride/flags/__init__.py
ShellPride/messages/__init__.py
ShellPride-0.0.3.dist-info/LICENSE
ShellPride-0.0.3.dist-info/METADATA
ShellPride-0.0.3.dist-info/WHEEL
ShellPride-0.0.3.dist-info/entry_points.txt
ShellPride-0.0.3.dist-info/top_level.txt
ShellPride-0.0.3.dist-info/RECORD
