Metadata-Version: 2.1
Name: ShellPride
Version: 0.0.3
Summary: Package for printing pride flag decorators in the shell.
Home-page: https://github.com/ccmorenos/ShellPride.git
Author: Catalina Moreno
Author-email: ccatamorenos@gmail.com
Maintainer: Catalina Moreno
Maintainer-email: ccatamorenos@gmail.com
License: MIT license
License-File: LICENSE
